VerilogBM-123-146.v
/*

Title:- AUTOMATED HOSPITAL MANAGEMENT SYSTEM

Team Members:- Mahir Jain (16CO123) AND Suraj Singh (16CO146)

Abstract:- 
The project implements an emergency room scenario in a hospital. Different patients suffering from varying degree of medical issues are brought for treatment. Following a straight-forward queue is not sufficient. Hence the system created assigns an ID and a priority to a patient (Inputs). When the doctor is ready to receive another patient, the highest priority patient is sent for treatment, with the ID and priority displayed (Outputs). An additional output of the number of patients is also given, to ensure the room does not exceed capacity. This can easily be extended to a larger scale system, with more doctors and patients. The system will help in easing decision making, and make the entire process more efficient.

Functionalities:- 
The system is capable of:-
1. Checking if room is full or not, and accordingly allowing an input to take place
2. Storing the patient information, including ID and Priority.
3. Updating automatically the number of patients/availability status.
4. Deciding which patient next gets the treatment from the doctor.
 
*/



//Module to implement main logic- that of the priority queue

// This is a behavioral module. It utilises registers to store the input, and upon being sent signal for dequeue, produces the required output by observing the priority bits that have been assigned.
module prioq(in,
			clk, //Clock signal
			out, //Output information/details of patient who is sent for treatment.
			ende //enqueue(0)/dequeue(1)-Control input given by user. 
			   );  //ADD FLAGS FOR FULL AND EMPTY CHECK IN THESE ()
	//DECLARATION
	parameter size = 15;	//Capacity of the queue.
 
	reg [3:0] arr[15:0]; //Array to store of length "size" to store four 4 bit values 

	reg [1:0] priority_array[15:0]; //Array to store each patients priority.

	input  [3:0]in;	//4 bit input, with 2 bits representing priority, and 2 bits representing Unique ID.

	input clk;	//Clock input

	input ende;	//Flag , 0- Enqueue, 1-Dequeue

	output reg  [3:0]out;	//4 bit output corresponding to the 4 bit input.

	reg [3:0] tmp; //temporary variable to swap front of queue with element with highest priority

	reg [1:0] tmp_priority;	// Temporary variable to hold priority.

	output reg isfull;	//Flag to check if the room is full/has reached capacity. 

	output reg isempty;	//Flag to check if the room is empty.

	integer count,i;		//Variable that keeps count of the number of patients presently in the room.

	//INITIAL
	initial 
	begin

	count<=0; //Number of patients is 0 initially.

	end

	//ALWAYS
	always@ (posedge clk)
	begin
		if(ende == 0) //inexpensive enqueue
		begin
			arr[count] <= in;	//Stores value in a serial-shift-register
			priority_array[count] <= in[3:2];  //Storing priority in register.
			count = count + 1;	//Updating count of patients.
		end

		else if(ende == 1) //O(n) dequeue. Checking if there's an element with higher priority and swapping if there is 
		begin
			for(i=0;i<count;i=i+1)
			begin
				if(priority_array[i] > priority_array[0]) //comparing priorities. If greater priority, swap.
				begin
					tmp =  arr[i];
					tmp_priority = priority_array[i];
					arr[i]  =  arr[0];
					priority_array[i]  =  priority_array[0];
					arr[0] = tmp;
					priority_array[0] = tmp_priority; 
				end
			end
			out =  arr[0]; //Removing from front of the queue.
			count = count - 1;	//Updating patient count.
		end

	end

endmodule

Verilog-123-146.v
/*

Title:- AUTOMATED HOSPITAL MANAGEMENT SYSTEM

Team Members:- Mahir Jain (16CO123) AND Suraj Singh (16CO146)

Abstract:- 
The project implements an emergency room scenario in a hospital. Different patients suffering from varying degree of medical issues are brought for treatment. Following a straight-forward queue is not sufficient. Hence the system created assigns an ID and a priority to a patient (Inputs). When the doctor is ready to receive another patient, the highest priority patient is sent for treatment, with the ID and priority displayed (Outputs). An additional output of the number of patients is also given, to ensure the room does not exceed capacity. This can easily be extended to a larger scale system, with more doctors and patients. The system will help in easing decision making, and make the entire process more efficient.

Functionalities:- 
The system is capable of:-
1. Checking if room is full or not, and accordingly allowing an input to take place
2. Storing the patient information, including ID and Priority.
3. Updating automatically the number of patients/availability status.
4. Deciding which patient next gets the treatment from the doctor.
 
*/

`timescale 1ns/10ps

//This is the testbench for the project. It is common to both Behavioral and Dataflow models.
//It will demonstrate the sequence in which patients receive treatment. The output can be viewed on terminal or as a waveform in GTKWave.



module test_circuit;

reg [3:0]in;	//4 bit input, with 2 bits representing priority, and 2 bits representing Unique ID.
reg clk;	//Clock input
reg ende;	//Flag , 0- Enqueue, 1-Dequeue
wire [3:0]out;	//4 bit output corresponding to the 4 bit input.

prioq p1(in,clk,out,ende); //Initiating module to implement the logic.

//Setting up clock pulse

initial
begin
clk <= 0;
end
always #5 clk = ~clk;

//Providing stimulus to circuit
initial 
begin
	//Initialise inputs
	ende <= 0;
	in <= 4'b0011; //Enqueue Priority-00 ID-11
	#10;
	in <= 4'b1010; //Enqueue Priority-10 ID-10
	#10;
	ende <= 1'b1;  //Dequeue requested
	#10;
	ende <= 0;     //Enqueue a patient
	in <= 4'b1101; //Enqueue Priority-11 ID-01
	#10;
	ende <= 1'b1;  //Dequeue requested
	#20;
	$finish;       //Stop simulation
end
initial 
begin
	//Displaying relevant outputs on the terminal/bash.
	$monitor("Time:- %t, Ende:- %b, in:- %b, out:- %b",$time,ende,in,out);
end
endmodule

test.vcd
$date
	Mon Nov  6 00:00:40 2017
$end
$version
	Icarus Verilog
$end
$timescale
	10ps
$end
$scope module test_circuit $end
$var wire 4 ! out [3:0] $end
$var reg 1 " clk $end
$var reg 1 # ende $end
$var reg 4 $ in [3:0] $end
$scope module p1 $end
$var wire 1 " clk $end
$var wire 1 # ende $end
$var wire 4 % in [3:0] $end
$var reg 1 & isempty $end
$var reg 1 ' isfull $end
$var reg 4 ( out [3:0] $end
$var reg 4 ) tmp [3:0] $end
$var reg 2 * tmp_priority [1:0] $end
$var integer 32 + count [31:0] $end
$var integer 32 , i [31:0] $end
$upscope $end
$upscope $end
$enddefinitions $end
#0
$dumpvars
bx ,
b0 +
bx *
bx )
bx (
x'
x&
b11 %
b11 $
0#
0"
bx !
$end
#500
b1 +
1"
#1000
b1010 $
b1010 %
0"
#1500
b10 +
1"
#2000
1#
0"
#2500
b1 +
b1010 !
b1010 (
b10 *
b1010 )
b10 ,
1"
#3000
b1101 $
b1101 %
0#
0"
#3500
b10 +
1"
#4000
1#
0"
#4500
b1 +
b1101 !
b1101 (
b11 *
b1101 )
b10 ,
1"
#5000
0"
#5500
b0 +
b1 ,
1"
